LICENSE
README.md
setup.py
omarpppl/__init__.py
omarpppl.egg-info/PKG-INFO
omarpppl.egg-info/SOURCES.txt
omarpppl.egg-info/dependency_links.txt
omarpppl.egg-info/top_level.txt