Metadata-Version: 2.1
Name: omarpppl
Version: 0.2
Summary: Omarrrrrv
Home-page: https://github.com/Omarail1/omarpoop.git
Author: omar Style
Author-email: omarllStyle@gmail.com
Classifier: Programming Language :: Python :: 3
Classifier: Programming Language :: Python :: 3.6
Classifier: Programming Language :: Python :: 3.7
Classifier: Programming Language :: Python :: 3.8
Classifier: Programming Language :: Python :: 3.9
Classifier: License :: OSI Approved :: MIT License
License-File: LICENSE
